{
    "Campaign1": {
        "id": "1",
        "name": "Print Series",
        "desc": "Deploy series of display print ads to bring strong awareness to the topic",
        "image1": "print1.jpg",
        "image2": "print2.jpg",
        "image3": "print3.jpg",
        "image4": "print4.jpg",
        "image5": "print5.jpg",
        "campBG": "printThumb.jpg"

    },
    "Campaign2": {
        "id": "2",
        "name": "Print Applications",
        "desc": "Deploy series of display print ads to bring strong awareness to the topic",
        "image1": "BigCityBillboardMockup.jpg",
        "image2": "StoreMockup.jpg",
        "image3": "BusMockup.jpg",
        "image4": "MetroBillboardMockup.jpg",
        "image5": "Jumbotron-Mockup.jpg",
        "campBG": "appThumb.jpg"

    },
    "Campaign3": {
        "id": "3",
        "name": "Social Media Campaign",
        "desc": "Strategic online marketing to core audience",
        "image1": "FacebookMockup.jpg",
        "image2": "Instagram.jpg",
        "image3": "print3.jpg",
        "image4": "print4.jpg",
        "image5": "print5.jpg",
        "campBG": "socialThumb.jpg"
    }
}